llmdk/__init__.py
llmdk/llmdk.py
llmdk/version.py
llmdk/providers/anthropic.py
llmdk/providers/groq.py
llmdk/providers/huggingface.py
llmdk/providers/interface.py
llmdk/providers/ollama.py
llmdk/providers/openai.py
llmdk-1.2410.3.dist-info/LICENSE
llmdk-1.2410.3.dist-info/METADATA
llmdk-1.2410.3.dist-info/WHEEL
llmdk-1.2410.3.dist-info/top_level.txt
llmdk-1.2410.3.dist-info/RECORD
