Metadata-Version: 2.1
Name: llmdk
Version: 1.2410.3
Summary: LLM Development Kit for common APIs
Author-email: "Rodrigo Martínez (brunneis)" <dev@brunneis.com>
License: GNU GENERAL PUBLIC LICENSE
Classifier: Development Status :: 4 - Beta
Classifier: Environment :: Console
Classifier: Intended Audience :: Developers
Classifier: License :: OSI Approved :: GNU General Public License v3 (GPLv3)
Classifier: Operating System :: POSIX :: Linux
Classifier: Programming Language :: Python :: 3.10
Classifier: Programming Language :: Python :: Implementation :: PyPy
Classifier: Topic :: Software Development :: Libraries :: Python Modules
Requires-Python: >=3.10
License-File: LICENSE
Requires-Dist: requests
Requires-Dist: openai
Requires-Dist: anthropic
Requires-Dist: groq
Requires-Dist: ollama
Requires-Dist: huggingface-hub
